LICENSE
p115dav/__init__.py
p115dav/__main__.py
p115dav/app.py
p115dav/db.py
p115dav/py.typed
p115dav/static/images/close.svg
p115dav/static/images/fancybox.svg
p115dav/static/images/favicon.svg
p115dav/static/images/fileball.svg
p115dav/static/images/iina.svg
p115dav/static/images/infuse.svg
p115dav/static/images/mpv.svg
p115dav/static/images/mxplayer-pro.svg
p115dav/static/images/mxplayer.svg
p115dav/static/images/nplayer.svg
p115dav/static/images/plyr.svg
p115dav/static/images/potplayer.svg
p115dav/static/images/stellarplayer.svg
p115dav/static/images/subtitle.svg
p115dav/static/images/vlc.svg
p115dav/views/base.jinja
p115dav/views/list.jinja
p115dav/views/search.html
p115dav/views/share_list.jinja
p115dav-0.0.10.4.dist-info/LICENSE
p115dav-0.0.10.4.dist-info/LICENSE_zh
p115dav-0.0.10.4.dist-info/METADATA
p115dav-0.0.10.4.dist-info/WHEEL
p115dav-0.0.10.4.dist-info/entry_points.txt
p115dav-0.0.10.4.dist-info/RECORD
