Metadata-Version: 2.1
Name: p115dav
Version: 0.0.10.4
Summary: 115 网盘 WebDAV 和 302 直链程序.
Home-page: https://github.com/ChenyangGao/p115client/tree/main/modules/p115dav
License: MIT
Keywords: python-115,webdav
Author: ChenyangGao
Author-email: wosiwujm@gmail.com
Requires-Python: >=3.12,<4.0
Classifier: Development Status :: 5 - Production/Stable
Classifier: Intended Audience :: Developers
Classifier: License :: OSI Approved :: MIT License
Classifier: Operating System :: OS Independent
Classifier: Programming Language :: Python
Classifier: Programming Language :: Python :: 3
Classifier: Programming Language :: Python :: 3.12
Classifier: Programming Language :: Python :: 3.13
Classifier: Programming Language :: Python :: 3 :: Only
Classifier: Topic :: Software Development
Classifier: Topic :: Software Development :: Libraries
Classifier: Topic :: Software Development :: Libraries :: Python Modules
Requires-Dist: a2wsgi (>=1.10.7)
Requires-Dist: blacksheep
Requires-Dist: cachedict (>=0.0.6)
Requires-Dist: httpagentparser
Requires-Dist: orjson
Requires-Dist: p115client (>=0.0.6.5)
Requires-Dist: p115pickcode (>=0.0.5.4)
Requires-Dist: path_predicate (>=0.0.1.1)
Requires-Dist: posixpatht (>=0.0.3)
Requires-Dist: pysubs2
Requires-Dist: python-dictattr (>=0.0.4)
Requires-Dist: python-encode_uri (>=0.0.3)
Requires-Dist: python-property (>=0.0.3)
Requires-Dist: python-sqlitedict (>=0.0.1.2)
Requires-Dist: python-texttools (>=0.0.3)
Requires-Dist: pyyaml
Requires-Dist: rich
Requires-Dist: uvicorn
Requires-Dist: wsgidav
Project-URL: Repository, https://github.com/ChenyangGao/p115client/tree/main/modules/p115dav
